{
  "aspectWidth": 4,
  "aspectHeight": 3,
  "enableKeyboardZoom": true,
  "enableKeyboardRotation": true,
  "enableKeyboardNavigation": true,
  "enableMouseTranslation": true,
  "enableMouseZoom": true,
  "enableMouseRotation": true,
  "enableMouseNavigation": true,
  "updateURLOnFrameChange": true,
  "frames": [
    {
      "frameId": "frame1853",
      "title": "Départ",
      "titleLevel": 0,
      "notes": "",
      "timeoutMs": 0,
      "timeoutEnable": false,
      "transitionDurationMs": 0,
      "showInFrameList": true,
      "showFrameNumber": false,
      "layerProperties": {
        "layer1": {
          "link": false,
          "referenceElementId": "ciel",
          "outlineElementId": "ciel",
          "transitionTimingFunction": "stepEnd",
          "transitionRelativeZoom": 0,
          "transitionPathId": ""
        },
        "layer2": {
          "link": false,
          "referenceElementId": "nuages-depart",
          "outlineElementId": "nuages-depart",
          "transitionTimingFunction": "stepEnd",
          "transitionRelativeZoom": 0,
          "transitionPathId": ""
        },
        "layer4": {
          "link": false,
          "referenceElementId": "arbres-depart",
          "outlineElementId": "arbres-depart",
          "transitionTimingFunction": "stepEnd",
          "transitionRelativeZoom": 0,
          "transitionPathId": ""
        },
        "layer5": {
          "link": false,
          "referenceElementId": "maisons-depart",
          "outlineElementId": "maisons-depart",
          "transitionTimingFunction": "stepEnd",
          "transitionRelativeZoom": 0,
          "transitionPathId": ""
        },
        "layer6": {
          "link": false,
          "referenceElementId": "voiture-depart",
          "outlineElementId": "voiture-depart",
          "transitionTimingFunction": "stepEnd",
          "transitionRelativeZoom": 0,
          "transitionPathId": ""
        },
        "__sozi_auto__": {
          "link": false,
          "referenceElementId": "ciel",
          "outlineElementId": "ciel",
          "transitionTimingFunction": "stepEnd",
          "transitionRelativeZoom": 0,
          "transitionPathId": ""
        }
      },
      "cameraStates": {
        "layer1": {
          "cx": 245.6693115234375,
          "cy": 113.38580322265625,
          "width": 151.18110656738293,
          "height": 113.38583374023445,
          "opacity": 1,
          "angle": 0,
          "clipped": true,
          "clipXOffset": 0,
          "clipYOffset": 0,
          "clipWidthFactor": 1,
          "clipHeightFactor": 1
        },
        "layer2": {
          "cx": 245.6693115234375,
          "cy": 245.6692352294922,
          "width": 151.18110656738293,
          "height": 113.38583374023445,
          "opacity": 1,
          "angle": 0,
          "clipped": true,
          "clipXOffset": 0,
          "clipYOffset": 0,
          "clipWidthFactor": 1,
          "clipHeightFactor": 1
        },
        "layer4": {
          "cx": 245.6693115234375,
          "cy": 377.95269775390625,
          "width": 151.18110656738287,
          "height": 113.38583374023443,
          "opacity": 1,
          "angle": 0,
          "clipped": true,
          "clipXOffset": 0,
          "clipYOffset": 0,
          "clipWidthFactor": 1,
          "clipHeightFactor": 1
        },
        "layer5": {
          "cx": 245.6693115234375,
          "cy": 510.2362060546875,
          "width": 151.18110656738287,
          "height": 113.38583374023443,
          "opacity": 1,
          "angle": 0,
          "clipped": true,
          "clipXOffset": 0,
          "clipYOffset": 0,
          "clipWidthFactor": 1,
          "clipHeightFactor": 1
        },
        "layer6": {
          "cx": 245.6693115234375,
          "cy": 642.5196533203125,
          "width": 151.18110656738293,
          "height": 113.38583374023445,
          "opacity": 1,
          "angle": 0,
          "clipped": true,
          "clipXOffset": 0,
          "clipYOffset": 0,
          "clipWidthFactor": 1,
          "clipHeightFactor": 1
        },
        "__sozi_auto__": {
          "cx": 245.6693115234375,
          "cy": 113.38580322265625,
          "width": 151.18110656738293,
          "height": 113.38583374023445,
          "opacity": 1,
          "angle": 0,
          "clipped": true,
          "clipXOffset": 0,
          "clipYOffset": 0,
          "clipWidthFactor": 1,
          "clipHeightFactor": 1
        }
      },
      "cameraOffsets": {
        "layer1": {
          "deltaX": 0,
          "deltaY": 0,
          "widthFactor": 1.0000000000000009,
          "heightFactor": 1.0000000000000007,
          "deltaAngle": 0
        },
        "layer2": {
          "deltaX": 0,
          "deltaY": 0,
          "widthFactor": 1.0000000000000009,
          "heightFactor": 1.0000000000000007,
          "deltaAngle": 0
        },
        "layer4": {
          "deltaX": 0,
          "deltaY": 0,
          "widthFactor": 1.0000000000000007,
          "heightFactor": 1.0000000000000007,
          "deltaAngle": 0
        },
        "layer5": {
          "deltaX": 0,
          "deltaY": 0,
          "widthFactor": 1.0000000000000007,
          "heightFactor": 1.0000000000000007,
          "deltaAngle": 0
        },
        "layer6": {
          "deltaX": 0,
          "deltaY": 0,
          "widthFactor": 1.0000000000000009,
          "heightFactor": 1.0000000000000007,
          "deltaAngle": 0
        },
        "__sozi_auto__": {
          "deltaX": 0,
          "deltaY": 0,
          "widthFactor": 1.0000000000000009,
          "heightFactor": 1.0000000000000007,
          "deltaAngle": 0
        }
      }
    },
    {
      "frameId": "frame1398",
      "title": "Arrivée",
      "titleLevel": 0,
      "notes": "",
      "timeoutMs": 0,
      "timeoutEnable": false,
      "transitionDurationMs": 5000,
      "showInFrameList": true,
      "showFrameNumber": false,
      "layerProperties": {
        "layer1": {
          "link": false,
          "referenceElementId": "ciel",
          "outlineElementId": "ciel",
          "transitionTimingFunction": "easeInOut",
          "transitionRelativeZoom": 0,
          "transitionPathId": ""
        },
        "layer2": {
          "link": false,
          "referenceElementId": "nuages-arrivee",
          "outlineElementId": "nuages-arrivee",
          "transitionTimingFunction": "easeInOut",
          "transitionRelativeZoom": 0,
          "transitionPathId": ""
        },
        "layer4": {
          "link": false,
          "referenceElementId": "arbres-arrivee",
          "outlineElementId": "arbres-arrivee",
          "transitionTimingFunction": "easeInOut",
          "transitionRelativeZoom": 0,
          "transitionPathId": ""
        },
        "layer5": {
          "link": false,
          "referenceElementId": "maisons-arrivee",
          "outlineElementId": "maisons-arrivee",
          "transitionTimingFunction": "easeInOut",
          "transitionRelativeZoom": 0,
          "transitionPathId": ""
        },
        "layer6": {
          "link": false,
          "referenceElementId": "voiture-arrivee",
          "outlineElementId": "voiture-arrivee",
          "transitionTimingFunction": "easeInOut",
          "transitionRelativeZoom": 0,
          "transitionPathId": ""
        },
        "__sozi_auto__": {
          "link": false,
          "referenceElementId": "ciel",
          "outlineElementId": "ciel",
          "transitionTimingFunction": "easeInOut",
          "transitionRelativeZoom": 0,
          "transitionPathId": ""
        }
      },
      "cameraStates": {
        "layer1": {
          "cx": 245.6693115234375,
          "cy": 113.38580322265625,
          "width": 151.18110656738293,
          "height": 113.38583374023445,
          "opacity": 1,
          "angle": 0,
          "clipped": true,
          "clipXOffset": 0,
          "clipYOffset": 0,
          "clipWidthFactor": 1,
          "clipHeightFactor": 1
        },
        "layer2": {
          "cx": 400.6299133300781,
          "cy": 245.6692352294922,
          "width": 151.18110656738293,
          "height": 113.38583374023445,
          "opacity": 1,
          "angle": 0,
          "clipped": true,
          "clipXOffset": 0,
          "clipYOffset": 0,
          "clipWidthFactor": 1,
          "clipHeightFactor": 1
        },
        "layer4": {
          "cx": 555.590576171875,
          "cy": 377.95269775390625,
          "width": 151.18110656738293,
          "height": 113.38583374023445,
          "opacity": 1,
          "angle": 0,
          "clipped": true,
          "clipXOffset": 0,
          "clipYOffset": 0,
          "clipWidthFactor": 1,
          "clipHeightFactor": 1
        },
        "layer5": {
          "cx": 710.5512084960938,
          "cy": 510.23614501953125,
          "width": 151.18110656738293,
          "height": 113.38583374023445,
          "opacity": 1,
          "angle": 0,
          "clipped": true,
          "clipXOffset": 0,
          "clipYOffset": 0,
          "clipWidthFactor": 1,
          "clipHeightFactor": 1
        },
        "layer6": {
          "cx": 170.0787353515625,
          "cy": 642.5196533203125,
          "width": 151.18110656738293,
          "height": 113.38583374023445,
          "opacity": 1,
          "angle": 0,
          "clipped": true,
          "clipXOffset": 0,
          "clipYOffset": 0,
          "clipWidthFactor": 1,
          "clipHeightFactor": 1
        },
        "__sozi_auto__": {
          "cx": 245.6693115234375,
          "cy": 113.38580322265625,
          "width": 151.18110656738293,
          "height": 113.38583374023445,
          "opacity": 1,
          "angle": 0,
          "clipped": true,
          "clipXOffset": 0,
          "clipYOffset": 0,
          "clipWidthFactor": 1,
          "clipHeightFactor": 1
        }
      },
      "cameraOffsets": {
        "layer1": {
          "deltaX": 0,
          "deltaY": 0,
          "widthFactor": 1.0000000000000009,
          "heightFactor": 1.0000000000000007,
          "deltaAngle": 0
        },
        "layer2": {
          "deltaX": 0,
          "deltaY": 0,
          "widthFactor": 1.0000000000000009,
          "heightFactor": 1.0000000000000007,
          "deltaAngle": 0
        },
        "layer4": {
          "deltaX": 0,
          "deltaY": 0,
          "widthFactor": 1.0000000000000009,
          "heightFactor": 1.0000000000000007,
          "deltaAngle": 0
        },
        "layer5": {
          "deltaX": 0,
          "deltaY": 0,
          "widthFactor": 1.0000000000000009,
          "heightFactor": 1.0000000000000007,
          "deltaAngle": 0
        },
        "layer6": {
          "deltaX": 0,
          "deltaY": 0,
          "widthFactor": 1.0000000000000009,
          "heightFactor": 1.0000000000000007,
          "deltaAngle": 0
        },
        "__sozi_auto__": {
          "deltaX": 0,
          "deltaY": 0,
          "widthFactor": 1.0000000000000009,
          "heightFactor": 1.0000000000000007,
          "deltaAngle": 0
        }
      }
    }
  ],
  "elementsToHide": [
    "voiture-depart",
    "voiture-arrivee",
    "maisons-depart",
    "maisons-arrivee",
    "arbres-depart",
    "arbres-arrivee",
    "nuages-depart",
    "nuages-arrivee"
  ],
  "selectedFrames": [
    "frame1853"
  ],
  "selectedLayers": [
    "layer1",
    "layer2",
    "layer4",
    "layer5",
    "layer6",
    "__sozi_auto__"
  ],
  "editableLayers": [
    "layer6",
    "layer5",
    "layer4",
    "layer2",
    "layer1"
  ]
}